scripts/__init__.py
scripts/cli.py
scripts/coverage.py
scripts/dev.py
cognyx_bom_sdk/__init__.py
cognyx_bom_sdk/__main__.py
cognyx_bom_sdk/client.py
cognyx_bom_sdk/models.py
cognyx_bom_sdk/cognyx/__init__.py
cognyx_bom_sdk/cognyx/__main__.py
cognyx_bom_sdk/cognyx/automation_runtime.py
cognyx_bom_sdk/cognyx/cognyx.py
cognyx_bom_sdk/cognyx/helpers.py
cognyx_bom_sdk/cognyx/models.py
cognyx_bom_sdk-0.6.6.dist-info/METADATA
cognyx_bom_sdk-0.6.6.dist-info/WHEEL
cognyx_bom_sdk-0.6.6.dist-info/entry_points.txt
cognyx_bom_sdk-0.6.6.dist-info/licenses/LICENSE
cognyx_bom_sdk-0.6.6.dist-info/RECORD
