Metadata-Version: 2.4
Name: cognyx-bom-sdk
Version: 0.6.6
Summary: Cognyx BOM SDK
Project-URL: Homepage, https://github.com/cognyx/cognyx-bom-sdk
Project-URL: Bug Tracker, https://github.com/cognyx/cognyx-bom-sdk/issues
Author: Cognyx
License: MIT License
License-File: LICENSE
Classifier: License :: OSI Approved :: MIT License
Classifier: Operating System :: OS Independent
Classifier: Programming Language :: Python :: 3
Classifier: Programming Language :: Python :: 3.8
Classifier: Programming Language :: Python :: 3.9
Classifier: Programming Language :: Python :: 3.10
Classifier: Programming Language :: Python :: 3.11
Requires-Python: >=3.11
Requires-Dist: dill>=0.3.9
Requires-Dist: pydantic>=2.0.0
Provides-Extra: dev
